{
    "model": "tabnet_trial_Experiment_outliers_Timestamp_50.0",
    "model_type": "TabNet",
    "label": "Experiment_outliers_Timestamp_50.0",
    "mcc_bin": 0.886259476906051,
    "mcc_mul": 0.8668089874071194,
    "mean_mcc": 0.8765342321565852,
    "cm_bin": [
        [
            217855,
            5340
        ],
        [
            3496,
            42520
        ]
    ],
    "cm_mul": [
        [
            218236,
            69,
            863,
            3830,
            61,
            23,
            73,
            1,
            3,
            36,
            0,
            0,
            0,
            0
        ],
        [
            11,
            11577,
            0,
            0,
            0,
            0,
            0,
            0,
            2,
            0,
            0,
            0,
            0,
            0
        ],
        [
            9,
            0,
            9307,
            243,
            0,
            0,
            0,
            0,
            0,
            0,
            0,
            0,
            0,
            0
        ],
        [
            714,
            0,
            0,
            6873,
            0,
            0,
            2,
            0,
            0,
            175,
            0,
            0,
            0,
            0
        ],
        [
            79,
            0,
            0,
            0,
            4695,
            0,
            0,
            0,
            0,
            0,
            0,
            0,
            0,
            0
        ],
        [
            0,
            0,
            0,
            0,
            0,
            2829,
            0,
            0,
            374,
            0,
            0,
            0,
            0,
            0
        ],
        [
            56,
            0,
            0,
            1,
            0,
            0,
            3116,
            0,
            0,
            0,
            0,
            0,
            0,
            0
        ],
        [
            2657,
            1,
            3,
            24,
            2,
            0,
            5,
            0,
            0,
            0,
            0,
            0,
            0,
            0
        ],
        [
            0,
            0,
            0,
            0,
            0,
            1357,
            0,
            0,
            996,
            0,
            0,
            0,
            0,
            0
        ],
        [
            15,
            0,
            0,
            252,
            0,
            0,
            45,
            0,
            0,
            371,
            0,
            0,
            0,
            0
        ],
        [
            97,
            0,
            0,
            3,
            0,
            0,
            4,
            0,
            0,
            84,
            0,
            0,
            0,
            0
        ],
        [
            27,
            0,
            0,
            0,
            0,
            0,
            0,
            0,
            0,
            0,
            0,
            0,
            0,
            0
        ],
        [
            7,
            0,
            0,
            0,
            0,
            0,
            0,
            0,
            0,
            0,
            0,
            0,
            0,
            0
        ],
        [
            3,
            0,
            0,
            0,
            0,
            0,
            0,
            0,
            0,
            0,
            0,
            0,
            0,
            0
        ]
    ],
    "feature_importance": {
        "Down/Up Ratio": 0.11229272205519068,
        "Dst Port": 0.15388162969640642,
        "FIN Flag Cnt": 0.043655543793111956,
        "Flow Pkts/s": 0.08213607228822452,
        "Fwd Pkt Len Max": 0.17340302149145567,
        "Init Bwd Win Byts": 0.1839882123560954,
        "Init Fwd Win Byts": 0.12563571814372362,
        "Protocol": 0.12500708017579176
    },
    "params": {
        "N_a": 16,
        "N_steps": 4,
        "gamma": 1.0,
        "lambda_sparse": 0.003967605077052991,
        "lr": 0.0015930522616241021,
        "batch_size": 4096,
        "mask_type": "sparsemax"
    },
    "metrics_binary": {
        "task": "Trial Experiment_outliers_Timestamp_50.0 - Binary Task",
        "accuracy": 0.9671781613678491,
        "f1": 0.9058758362094678,
        "mcc": 0.886259476906051,
        "auc": 0.9763175136871465
    },
    "metrics_multiclass": {
        "task": "Trial Experiment_outliers_Timestamp_50.0 - Multiclass Task",
        "accuracy": 0.958356085003956,
        "f1": 0.532005448444158,
        "mcc": 0.8668089874071194,
        "auc": NaN
    }
}