{
    "model": "experiments/cnn_lstm_trial_Experiment_labels_Protocol_5.0.pt",
    "model_type": "CNN-LSTM",
    "label": "Experiment_labels_Protocol_5.0",
    "mcc_bin": 0.7276101031702843,
    "mcc_mul": 0.6409480970927807,
    "mean_mcc": 0.6842791001315325,
    "val_loss": 0.8066428960966212,
    "cm_bin": [
        [
            22107,
            136
        ],
        [
            1807,
            2813
        ]
    ],
    "cm_mul": [
        [
            22213,
            25,
            0,
            3,
            0,
            0,
            0,
            0,
            2,
            0,
            0,
            0,
            0
        ],
        [
            1,
            1170,
            0,
            0,
            0,
            0,
            0,
            0,
            0,
            0,
            0,
            0,
            0
        ],
        [
            987,
            0,
            0,
            1,
            0,
            0,
            0,
            0,
            0,
            0,
            0,
            0,
            0
        ],
        [
            38,
            88,
            0,
            635,
            0,
            0,
            0,
            0,
            0,
            0,
            0,
            0,
            0
        ],
        [
            474,
            0,
            0,
            0,
            0,
            0,
            0,
            0,
            0,
            0,
            0,
            0,
            0
        ],
        [
            159,
            150,
            0,
            0,
            0,
            0,
            0,
            0,
            0,
            0,
            0,
            0,
            0
        ],
        [
            116,
            198,
            0,
            0,
            0,
            0,
            0,
            0,
            0,
            0,
            0,
            0,
            0
        ],
        [
            274,
            1,
            0,
            0,
            0,
            0,
            0,
            0,
            0,
            0,
            0,
            0,
            0
        ],
        [
            0,
            0,
            0,
            1,
            0,
            0,
            0,
            0,
            229,
            0,
            0,
            0,
            0
        ],
        [
            26,
            49,
            0,
            0,
            0,
            0,
            0,
            0,
            0,
            0,
            0,
            0,
            0
        ],
        [
            19,
            0,
            0,
            0,
            0,
            0,
            0,
            0,
            0,
            0,
            0,
            0,
            0
        ],
        [
            3,
            0,
            0,
            0,
            0,
            0,
            0,
            0,
            0,
            0,
            0,
            0,
            0
        ],
        [
            1,
            0,
            0,
            0,
            0,
            0,
            0,
            0,
            0,
            0,
            0,
            0,
            0
        ]
    ],
    "feature_importance": {
        "Down/Up Ratio": 0.010772833723653627,
        "Dst Port": 0.532552693208431,
        "FIN Flag Cnt": 0.0004683840749415835,
        "Flow Pkts/s": 0.13770491803278784,
        "Fwd Pkt Len Max": 0.3667447306791579,
        "Init Bwd Win Byts": 0.04355971896955469,
        "Init Fwd Win Byts": 1.0,
        "Protocol": 0.028571428571428213
    },
    "params": {
        "nb_filters": 32,
        "kernel_size": 3,
        "lstm_units_1": 128,
        "lstm_units_2": 256,
        "dropout": 0.1,
        "lr": 0.0008204643365323959,
        "batch_size": 4096
    },
    "metrics_binary": {
        "task": "Trial Experiment_labels_Protocol_5.0 - Binary Task",
        "accuracy": 0.9276700294084801,
        "f1": 0.7432950191570882,
        "mcc": 0.7276101031702843,
        "auc": 0.9311770539999644
    },
    "metrics_multiclass": {
        "task": "Trial Experiment_labels_Protocol_5.0 - Multiclass Task",
        "accuracy": 0.9026169824665897,
        "f1": 0.2826734052882279,
        "mcc": 0.6409480970927807,
        "auc": 0.9034383384995952
    }
}