{
    "model": "tabnet_trial_Experiment_labels_Protocol_1.0",
    "model_type": "TabNet",
    "label": "Experiment_labels_Protocol_1.0",
    "mcc_bin": 0.8785489238361156,
    "mcc_mul": 0.8499966931021019,
    "mean_mcc": 0.8642728084691087,
    "cm_bin": [
        [
            216847,
            6216
        ],
        [
            3268,
            42344
        ]
    ],
    "cm_mul": [
        [
            215688,
            135,
            1596,
            5422,
            103,
            9,
            72,
            0,
            9,
            29,
            0,
            0,
            0,
            0,
            0
        ],
        [
            10,
            11447,
            0,
            0,
            0,
            0,
            0,
            0,
            0,
            0,
            0,
            0,
            0,
            0,
            0
        ],
        [
            9,
            0,
            9353,
            221,
            0,
            0,
            0,
            0,
            0,
            0,
            0,
            0,
            0,
            0,
            0
        ],
        [
            139,
            0,
            0,
            7279,
            0,
            0,
            0,
            0,
            0,
            226,
            0,
            0,
            0,
            0,
            0
        ],
        [
            96,
            0,
            0,
            0,
            4650,
            0,
            0,
            0,
            0,
            0,
            0,
            0,
            0,
            0,
            0
        ],
        [
            0,
            0,
            0,
            0,
            0,
            2487,
            0,
            0,
            671,
            0,
            0,
            0,
            0,
            0,
            0
        ],
        [
            51,
            0,
            0,
            0,
            0,
            0,
            3089,
            0,
            1,
            0,
            0,
            0,
            0,
            0,
            0
        ],
        [
            2529,
            1,
            35,
            42,
            6,
            0,
            9,
            0,
            0,
            0,
            0,
            0,
            0,
            0,
            0
        ],
        [
            0,
            0,
            0,
            0,
            0,
            1036,
            0,
            0,
            1277,
            0,
            0,
            0,
            0,
            0,
            0
        ],
        [
            23,
            0,
            0,
            240,
            0,
            0,
            126,
            0,
            0,
            306,
            0,
            0,
            0,
            0,
            0
        ],
        [
            102,
            0,
            0,
            3,
            0,
            0,
            0,
            0,
            0,
            1,
            100,
            0,
            0,
            0,
            0
        ],
        [
            29,
            0,
            0,
            0,
            0,
            0,
            0,
            0,
            0,
            0,
            0,
            0,
            0,
            0,
            0
        ],
        [
            11,
            0,
            2,
            0,
            0,
            0,
            0,
            0,
            0,
            0,
            0,
            0,
            0,
            0,
            0
        ],
        [
            3,
            0,
            1,
            0,
            0,
            0,
            0,
            0,
            0,
            0,
            0,
            0,
            0,
            0,
            0
        ],
        [
            1,
            0,
            0,
            0,
            0,
            0,
            0,
            0,
            0,
            0,
            0,
            0,
            0,
            0,
            0
        ]
    ],
    "feature_importance": {
        "Down/Up Ratio": 0.13172172137272625,
        "Dst Port": 0.15202187675704773,
        "FIN Flag Cnt": 0.04947973855205705,
        "Flow Pkts/s": 0.13090884417356138,
        "Fwd Pkt Len Max": 0.19514600696387993,
        "Init Bwd Win Byts": 0.09781287456813116,
        "Init Fwd Win Byts": 0.15635910296276814,
        "Protocol": 0.08654983464982839
    },
    "params": {
        "N_a": 16,
        "N_steps": 4,
        "gamma": 1.0,
        "lambda_sparse": 0.003967605077052991,
        "lr": 0.0015930522616241021,
        "batch_size": 4096,
        "mask_type": "sparsemax"
    },
    "metrics_binary": {
        "task": "Trial Experiment_labels_Protocol_1.0 - Binary Task",
        "accuracy": 0.9647008467479297,
        "f1": 0.8992906596440555,
        "mcc": 0.8785489238361156,
        "auc": 0.9718502904363944
    },
    "metrics_multiclass": {
        "task": "Trial Experiment_labels_Protocol_1.0 - Multiclass Task",
        "accuracy": 0.951618125988648,
        "f1": 0.5331929158131256,
        "mcc": 0.8499966931021019,
        "auc": 0.8533246861955619
    }
}