{
    "model": "tabnet_trial_Experiment_noise_Down_Up Ratio_20.0",
    "model_type": "TabNet",
    "label": "Experiment_noise_Down_Up Ratio_20.0",
    "mcc_bin": 0.8967925609689685,
    "mcc_mul": 0.8760172450753347,
    "mean_mcc": 0.8864049030221517,
    "cm_bin": [
        [
            218348,
            4847
        ],
        [
            3159,
            42857
        ]
    ],
    "cm_mul": [
        [
            218579,
            56,
            882,
            3539,
            37,
            18,
            43,
            0,
            7,
            33,
            1,
            0,
            0,
            0
        ],
        [
            9,
            11577,
            0,
            0,
            0,
            2,
            0,
            0,
            2,
            0,
            0,
            0,
            0,
            0
        ],
        [
            9,
            0,
            9307,
            243,
            0,
            0,
            0,
            0,
            0,
            0,
            0,
            0,
            0,
            0
        ],
        [
            415,
            0,
            0,
            7302,
            0,
            0,
            2,
            0,
            0,
            45,
            0,
            0,
            0,
            0
        ],
        [
            25,
            0,
            0,
            0,
            4749,
            0,
            0,
            0,
            0,
            0,
            0,
            0,
            0,
            0
        ],
        [
            0,
            0,
            0,
            0,
            0,
            2836,
            0,
            0,
            367,
            0,
            0,
            0,
            0,
            0
        ],
        [
            52,
            0,
            0,
            1,
            0,
            0,
            3120,
            0,
            0,
            0,
            0,
            0,
            0,
            0
        ],
        [
            2639,
            1,
            5,
            42,
            2,
            0,
            2,
            0,
            1,
            0,
            0,
            0,
            0,
            0
        ],
        [
            0,
            0,
            0,
            0,
            0,
            1363,
            0,
            0,
            990,
            0,
            0,
            0,
            0,
            0
        ],
        [
            15,
            0,
            0,
            395,
            0,
            0,
            43,
            0,
            0,
            230,
            0,
            0,
            0,
            0
        ],
        [
            95,
            0,
            0,
            1,
            0,
            0,
            4,
            4,
            0,
            9,
            75,
            0,
            0,
            0
        ],
        [
            27,
            0,
            0,
            0,
            0,
            0,
            0,
            0,
            0,
            0,
            0,
            0,
            0,
            0
        ],
        [
            7,
            0,
            0,
            0,
            0,
            0,
            0,
            0,
            0,
            0,
            0,
            0,
            0,
            0
        ],
        [
            3,
            0,
            0,
            0,
            0,
            0,
            0,
            0,
            0,
            0,
            0,
            0,
            0,
            0
        ]
    ],
    "feature_importance": {
        "Down/Up Ratio": 0.06587190785785416,
        "Dst Port": 0.16396848686068224,
        "FIN Flag Cnt": 0.07093870269267645,
        "Flow Pkts/s": 0.08295071323668642,
        "Fwd Pkt Len Max": 0.06496935679276691,
        "Init Bwd Win Byts": 0.1898492988469991,
        "Init Fwd Win Byts": 0.17058143803988374,
        "Protocol": 0.19087009567245097
    },
    "params": {
        "N_a": 16,
        "N_steps": 4,
        "gamma": 1.0,
        "lambda_sparse": 0.003967605077052991,
        "lr": 0.0015930522616241021,
        "batch_size": 4096,
        "mask_type": "sparsemax"
    },
    "metrics_binary": {
        "task": "Trial Experiment_noise_Down_Up Ratio_20.0 - Binary Task",
        "accuracy": 0.9702612448971253,
        "f1": 0.9145753307725139,
        "mcc": 0.8967925609689685,
        "auc": 0.9777393839498109
    },
    "metrics_multiclass": {
        "task": "Trial Experiment_noise_Down_Up Ratio_20.0 - Multiclass Task",
        "accuracy": 0.9611977222327468,
        "f1": 0.5695490324877523,
        "mcc": 0.8760172450753347,
        "auc": NaN
    }
}