{
    "model": "tabnet_trial_Experiment_missing_Timestamp_75.0",
    "model_type": "TabNet",
    "label": "Experiment_missing_Timestamp_75.0",
    "mcc_bin": 0.885186950431019,
    "mcc_mul": 0.8667336776590574,
    "mean_mcc": 0.8759603140450383,
    "cm_bin": [
        [
            217325,
            5870
        ],
        [
            3139,
            42877
        ]
    ],
    "cm_mul": [
        [
            217644,
            76,
            863,
            4399,
            74,
            5,
            67,
            0,
            17,
            31,
            10,
            0,
            9,
            0
        ],
        [
            1,
            11588,
            0,
            0,
            0,
            0,
            1,
            0,
            0,
            0,
            0,
            0,
            0,
            0
        ],
        [
            9,
            0,
            9307,
            243,
            0,
            0,
            0,
            0,
            0,
            0,
            0,
            0,
            0,
            0
        ],
        [
            282,
            0,
            0,
            7480,
            0,
            0,
            0,
            0,
            0,
            2,
            0,
            0,
            0,
            0
        ],
        [
            96,
            0,
            0,
            0,
            4678,
            0,
            0,
            0,
            0,
            0,
            0,
            0,
            0,
            0
        ],
        [
            1,
            0,
            0,
            0,
            0,
            2494,
            0,
            0,
            708,
            0,
            0,
            0,
            0,
            0
        ],
        [
            61,
            0,
            0,
            1,
            0,
            0,
            3111,
            0,
            0,
            0,
            0,
            0,
            0,
            0
        ],
        [
            2646,
            0,
            3,
            34,
            0,
            1,
            8,
            0,
            0,
            0,
            0,
            0,
            0,
            0
        ],
        [
            1,
            0,
            0,
            0,
            0,
            1107,
            0,
            0,
            1245,
            0,
            0,
            0,
            0,
            0
        ],
        [
            15,
            0,
            0,
            394,
            0,
            0,
            51,
            0,
            0,
            223,
            0,
            0,
            0,
            0
        ],
        [
            97,
            0,
            0,
            3,
            0,
            0,
            4,
            0,
            0,
            0,
            84,
            0,
            0,
            0
        ],
        [
            27,
            0,
            0,
            0,
            0,
            0,
            0,
            0,
            0,
            0,
            0,
            0,
            0,
            0
        ],
        [
            7,
            0,
            0,
            0,
            0,
            0,
            0,
            0,
            0,
            0,
            0,
            0,
            0,
            0
        ],
        [
            3,
            0,
            0,
            0,
            0,
            0,
            0,
            0,
            0,
            0,
            0,
            0,
            0,
            0
        ]
    ],
    "feature_importance": {
        "Down/Up Ratio": 0.14369678397538582,
        "Dst Port": 0.12278587525003512,
        "FIN Flag Cnt": 0.04349521053392331,
        "Flow Pkts/s": 0.10048225057811286,
        "Fwd Pkt Len Max": 0.13756262442540554,
        "Init Bwd Win Byts": 0.170832772785689,
        "Init Fwd Win Byts": 0.16454561069196438,
        "Protocol": 0.11659887175948386
    },
    "params": {
        "N_a": 16,
        "N_steps": 4,
        "gamma": 1.0,
        "lambda_sparse": 0.003967605077052991,
        "lr": 0.0015930522616241021,
        "batch_size": 4096,
        "mask_type": "sparsemax"
    },
    "metrics_binary": {
        "task": "Trial Experiment_missing_Timestamp_75.0 - Binary Task",
        "accuracy": 0.9665355427527107,
        "f1": 0.9049312495383219,
        "mcc": 0.885186950431019,
        "auc": 0.9768034764949172
    },
    "metrics_multiclass": {
        "task": "Trial Experiment_missing_Timestamp_75.0 - Multiclass Task",
        "accuracy": 0.9578137594674809,
        "f1": 0.5705498409681923,
        "mcc": 0.8667336776590574,
        "auc": NaN
    }
}