{
    "model": "experiments/cnn_lstm_trial_Experiment_outliers_FIN Flag Cnt_5.0.pt",
    "model_type": "CNN-LSTM",
    "label": "Experiment_outliers_FIN Flag Cnt_5.0",
    "mcc_bin": 0.7610009859404309,
    "mcc_mul": 0.7465159666990735,
    "mean_mcc": 0.7537584763197522,
    "val_loss": 0.5823240828301225,
    "cm_bin": [
        [
            22295,
            36
        ],
        [
            1684,
            2902
        ]
    ],
    "cm_mul": [
        [
            22311,
            0,
            0,
            3,
            0,
            4,
            13,
            0,
            0,
            0,
            0,
            0,
            0
        ],
        [
            0,
            1159,
            0,
            0,
            0,
            0,
            0,
            0,
            0,
            0,
            0,
            0,
            0
        ],
        [
            941,
            0,
            0,
            0,
            0,
            0,
            0,
            0,
            0,
            0,
            0,
            0,
            0
        ],
        [
            58,
            0,
            0,
            724,
            0,
            0,
            0,
            0,
            0,
            0,
            0,
            0,
            0
        ],
        [
            466,
            0,
            0,
            0,
            0,
            0,
            0,
            0,
            0,
            0,
            0,
            0,
            0
        ],
        [
            2,
            0,
            0,
            0,
            0,
            296,
            0,
            0,
            18,
            0,
            0,
            0,
            0
        ],
        [
            43,
            0,
            0,
            12,
            0,
            0,
            271,
            0,
            0,
            0,
            0,
            0,
            0
        ],
        [
            270,
            0,
            0,
            0,
            0,
            0,
            0,
            0,
            0,
            0,
            0,
            0,
            0
        ],
        [
            0,
            0,
            0,
            0,
            0,
            0,
            0,
            0,
            235,
            0,
            0,
            0,
            0
        ],
        [
            37,
            1,
            0,
            12,
            0,
            0,
            17,
            0,
            0,
            0,
            0,
            0,
            0
        ],
        [
            19,
            0,
            0,
            0,
            0,
            0,
            0,
            0,
            0,
            0,
            0,
            0,
            0
        ],
        [
            3,
            0,
            0,
            0,
            0,
            0,
            0,
            0,
            0,
            0,
            0,
            0,
            0
        ],
        [
            2,
            0,
            0,
            0,
            0,
            0,
            0,
            0,
            0,
            0,
            0,
            0,
            0
        ]
    ],
    "feature_importance": {
        "Down/Up Ratio": 0.03887884267631114,
        "Dst Port": 0.6225135623869809,
        "FIN Flag Cnt": 0.0,
        "Flow Pkts/s": 0.10397830018083229,
        "Fwd Pkt Len Max": 0.3865280289330922,
        "Init Bwd Win Byts": 0.15506329113924072,
        "Init Fwd Win Byts": 1.0,
        "Protocol": 0.10895117540687198
    },
    "params": {
        "nb_filters": 32,
        "kernel_size": 3,
        "lstm_units_1": 128,
        "lstm_units_2": 256,
        "dropout": 0.1,
        "lr": 0.0008204643365323959,
        "batch_size": 4096
    },
    "metrics_binary": {
        "task": "Trial Experiment_outliers_FIN Flag Cnt_5.0 - Binary Task",
        "accuracy": 0.936099862540402,
        "f1": 0.7713981924508241,
        "mcc": 0.7610009859404309,
        "auc": 0.9616178321941833
    },
    "metrics_multiclass": {
        "task": "Trial Experiment_outliers_FIN Flag Cnt_5.0 - Multiclass Task",
        "accuracy": 0.9286324627558792,
        "f1": 0.4378979483132036,
        "mcc": 0.7465159666990735,
        "auc": NaN
    }
}